[
    {
        "div_width": 30, 
        "c_h": 10, 
        "max_height": 456, 
        "id": "meta-data", 
        "midline": 398, 
        "word": "Success", 
        "caption": "", 
        "start_x": 50, 
        "s_f": 15.57632398753894, 
        "words_included": "success", 
        "div_spacing": 10, 
        "raphlines": [
            "M40,397L40,528S40,538,50,538L70,538S80,538,80,542S80,546,90,546L110,546S120,546,120,536L120,478S120,468,130,468L150,468S160,468,160,464S160,460,170,460L190,460S200,460,200,468S200,476,210,476L230,476S240,476,240,486L240,528S240,538,250,538L270,538S280,538,280,528L280,493S280,483,290,483L310,483S320,483,320,493L320,520S320,530,330,530L350,530S360,530,360,540L360,544S360,554,370,554L390,554S400,554,400,544L400,509S400,499,410,499L430,499S440,499,440,489L440,470S440,460,450,460L470,460S480,460,480,470L480,551S480,561,490,561L510,561S520,561,520,551L520,532S520,522,530,522L550,522S560,522,560,512L560,509S560,499,570,499L590,499S600,499,600,509L600,544S600,554,610,554L630,554S640,554,640,564L640,582S640,592,650,592L670,592S680,592,680,602L680,621S680,631,690,631L710,631S720,631,720,621L720,540S720,530,730,530L750,530S760,530,760,520L760,486S760,476,770,476L790,476S800,476,800,486L800,528S800,538,810,538L830,538S840,538,840,528L840,398L840,397", 
            "M40,398L40,268S40,258,50,258L70,258S80,258,80,254S80,250,90,250L110,250S120,250,120,260L120,318S120,328,130,328L150,328S160,328,160,332S160,336,170,336L190,336S200,336,200,328S200,320,210,320L230,320S240,320,240,310L240,268S240,258,250,258L270,258S280,258,280,268L280,303S280,313,290,313L310,313S320,313,320,303L320,276S320,266,330,266L350,266S360,266,360,256L360,252S360,242,370,242L390,242S400,242,400,252L400,287S400,297,410,297L430,297S440,297,440,307L440,326S440,336,450,336L470,336S480,336,480,326L480,245S480,235,490,235L510,235S520,235,520,245L520,264S520,274,530,274L550,274S560,274,560,284L560,287S560,297,570,297L590,297S600,297,600,287L600,252S600,242,610,242L630,242S640,242,640,232L640,214S640,204,650,204L670,204S680,204,680,194L680,175S680,165,690,165L710,165S720,165,720,175L720,256S720,266,730,266L750,266S760,266,760,276L760,310S760,320,770,320L790,320S800,320,800,310L800,268S800,258,810,258L830,258S840,258,840,268L840,398"
        ], 
        "y_spacing": 165
    }, 
    {
        "sentence_index": 0, 
        "sentences": [
            "Letter Added for Luck Early in her radio career, she changed the spelling of her first name to Ireene with three ''e's'' when she was told by a numerologist that one more letter would bring her great success.", 
            "Letter Added for Luck Early in her radio career, she changed the spelling of her first name to Ireene with three ''e's'' when she was told by a numerologist that one more letter would bring her great success.", 
            "'' In 1935 she married Vincent Sheean, the noted American foreign correspondent, whose book ''Personal History'' was published to great success that year.", 
            "'' Other credits included work as executive producer or co-producer on the films ''The Last of Sheila,'' ''The Seven Percent Solution,'' ''Nijinsky,'' ''Pennies From Heaven'' and ''The Secret of My Success.", 
            "It was a tremendous success, running for more than three years.", 
            "'' Developed a Following Her film career rocketed with the success of ''Kind Hearts and Coronets,'' and Miss Greenwood gained a following on both sides of the Atlantic.", 
            "'' Married in 1938 The success of ''Loch Lomond'' led to an engagement for her at the Onyx Club on 52d Street.", 
            "She had a brilliant success in the world premiere of ''Casanova'' in 1928 and thereafter devoted her energies mainly to operetta.", 
            "In fact, she attributed part of her success to not hesitating to drop writers who displeased her.", 
            "Dalida, whose real name was Yolande Gigliotti, was born in 1933 and was an entertainment success in Europe and the Middle East for more than 30 years.", 
            "Miss Hartman enjoyed sudden success as a film actress following her ''Patch'' role and Academy Award nomination, but her career declined in succeeding years.", 
            "''That initial success beat me down,'' Miss Hartman, a tense, fragile-looking redhead, said in a 1969 interview.", 
            "In 1962, with the release of the film versions of ''Summer and Smoke'' and ''Sweet Bird of Youth,'' she found herself, after 10 years on the stage, being hailed as an ''overnight success.", 
            "Meeting with little success, she decided to return to Australia by way of New York.", 
            "'' Mary Astor was born Lucile Langhanke on May 3, 1906, in Quincy, Ill., the only child of the former Helen Vasconcells, an American, and Otto Ludwig Wilhelm Langhanke, a German immigrant who made an uncertain income from such diverse activities as teaching German and poultry farming until he began to cash in on his daughter's film success.", 
            "'' It was a box-office success, as was her next play, ''Margin for Error,'' which purveyed a modish anti-Nazism.", 
            "The work, ''Concerto in Three Rhythms,'' was such a success that the next year, another Whiteman commission, ''Symphonic Waltzes,'' followed."
        ], 
        "height": 270, 
        "rate": 18, 
        "start_y": 263, 
        "id": 0
    }, 
    {
        "sentence_index": 0, 
        "sentences": [
            "'' Known as a character actress, she had roles in more than 50 films, including the ''Gidget'' movies, ''The Blue Gardenia,'' ''My Sister Eileen,'' ''My Man Godfrey,'' ''The Thief of Damascus,'' ''The Sweet Smell of Success'' and ''Tora, Tora, Tora.", 
            "True to the family tradition, he went into the lumber business in Rockland, Me., and made a success of it.", 
            "'' But a good notice doesn't pay any bills, and for most of the 1930's Mrs. Nevelson had no success and little or no money.", 
            "'' As much as any artist of her generation, Mrs. Nevelson had to wait for success.", 
            "Mrs. Nevelson never allowed success to alter her way of life.", 
            "Despite her later success, he went on to say, Mrs. Nevelson ''remained extraordinarily independent of her reputation and other people's reputations.", 
            "'' 'I Always Knew I Was Great' Speaking also of Mrs. Nevelson's belief in herself as a vital factor in her work, Miss Diamonstein recalled once asking her how she had survived during her many years of obscurity before success.", 
            "Explanation of Success Although her books were not received enthusiastically by reviewers, they were immensely successful.", 
            "'' When the star fell ill, Miss Graham went on in her place, and, of course, was a smashing success, she said.", 
            "Irmgard Seefried, a German-born Austrian soprano who gained great success in the postwar years in operas of Mozart and Richard Strauss, died of cancer yesterday in Vienna."
        ], 
        "height": 286, 
        "rate": 19, 
        "start_y": 255, 
        "id": 1
    }, 
    {
        "sentence_index": 0, 
        "sentences": [
            "In 1914, she was hired for a minor role in ''Not Likely,'' produced by Andre Charlot, a Frenchman who had brought to London, with great success, the concept of the little revue of fast-paced, sophisticated songs, skits and blackouts.", 
            "The couple went to New York in 1936 and he joined WOR, where he gained success with a program on books and current events.", 
            "'' 'I Lose Myself in the Plot' Long after the novel's international success, Miss du Maurier said she could never understand why it had become an instant favorite that eventually sold over a million hardcover copies.", 
            "In 1958 Ms. Henry and two other members of the Visiting Nurses Association started the program in Rochester, N.Y., after they had seen its success in England.", 
            "After the success of the novel, Soho Press issued ''Come to Africa and Save Your Marriage,'' Mrs. Worrick's collection of short stories in which she told of the difficulties of various people -Peace Corps volunteers, foreign academics, Indians, American blacks and white hunters left behind by colonial empires - in finding their way in black Africa.", 
            "But they also said her success was partly attributable to personality traits for which they criticized her and to which she freely confessed: a fondness for gossip and scandal, a fear of becoming poor and a craving for power or, as she called it, influence.", 
            "It was an immediate success.", 
            "The film was a success, and its producer, Warner Brothers, signed Miss Davis to her first contract.", 
            "Friends and Enemies  Fonda, Crawford, Cagney and Flynn Having settled into character acting, Miss Davis in 1961 scored a success as the gin-soaked ''bag lady'' Apple Annie in ''Pocketful of Miracles.", 
            "She repeated her success in a 1932 revival on Broadway.", 
            "Their father is Dino De Laurentiis, the producer whom Miss Mangano married in 1949 soon after the release of ''Bitter Rice,'' his first international success."
        ], 
        "height": 130, 
        "rate": 9, 
        "start_y": 333, 
        "id": 2
    }, 
    {
        "sentence_index": 0, 
        "sentences": [
            "She then began to direct and had a success with her first effort, ''Neige'' (''Snow''), a 1981 docudrama about drug trafficking that she worked on with Jean-Henri Roger.", 
            "M-G-M then co-starred the couple in ''Love,'' a 1927 modern-dress version of Tolstoy's ''Anna Karenina,'' another huge success.", 
            "He changed the station's format from pop to classical, and the couple presided over its success under the new call letters.", 
            "In 1963 she scored her first major success, as Countess Adele in Rossini's ''Count Ory.", 
            "Miss Glanville-Hicks enjoyed her greatest activity and success in the United States, and became a citizen in 1948.", 
            "'' After that film's success, the offers poured in.", 
            "A leading proponent of good nutrition, Mrs. Roth wrote ''The Mood Control Diet,'' ''Reversing Health Risks,'' ''The Executive Success Diet'' and ''Aerobic Nutrition,'' among other books.", 
            "Success, With the Help of a Cat Miss Arden made her film debut in a 1937 grade-B melodrama called \"Oh, Doctor,\" in which she disastrously played a gun moll.", 
            "\" The key to her first Broadway success, in 1938 in the Cole Porter musical, \"Leave It to Me,\" was her innate ability to combine innocence and insouciance.", 
            "Her overnight success on Broadway on Nov. 9, 1938 put her on the cover of Life magazine and drew the attention of Hollywood.", 
            "\" Several months later, the 1960 television version of \"Peter Pan\" was shown again, with great success.", 
            "\" She said she wrote it \"because of so many requests from friends and fans who asked me to tell them the secret of success."
        ], 
        "height": 114, 
        "rate": 8, 
        "start_y": 341, 
        "id": 3
    }, 
    {
        "sentence_index": 0, 
        "sentences": [
            "Carol Channing performed a tribute to Miss Martin that put new words to \"My Heart Belongs to Daddy,\" the song that propelled Miss Martin to Broadway success in 1938 in Cole Porter's \"Leave It To Me.", 
            "Performing regularly, sometimes annually, in the United States for 15 years, the team was unsurpassed in critical acclaim, box office success and public adulation.", 
            "Their success prompted her to found the Chicago Opera Ballet in 1956, a touring company that featured ballets inspired by operas and operettas.", 
            "In 1976, Mrs. Taylor said, \"I think we'll be a great success, because we have a superb collection and people are becoming more and more aware of how design relates to the quality of life.", 
            "The writing team's first novel, \"Hurry Sundown\" (1965), was an instant commercial success.", 
            "Her first stage success was in the 1943 production of the comedy \"Kiss and Tell,\" in which she appeared for 14 months.", 
            "First Success Finally, at the age of 20, she enjoyed her first big success, opposite Sidney Blackmer in Arthur Richman's \"Not So Long Ago.", 
            "Start of a Team Major success began after the 1958 Greenwich Village Circle in the Square production of Edwin Justus Mayer's \"Children of Darkness,\" in which she appeared with another up-and-coming young performer, George C. Scott.", 
            "Major success began after the 1958 Greenwich Village Circle in the Square production of Edwin Justus Mayer's \"Children of Darkness,\" in which she appeared with another up-and-coming performer, George C. Scott.", 
            "But her biggest success was the editing of \"The Weight Watchers Program Cookbook\" by Jean Nidetch, which sold millions of copies."
        ], 
        "height": 146, 
        "rate": 10, 
        "start_y": 325, 
        "id": 4
    }, 
    {
        "sentence_index": 0, 
        "sentences": [
            "Mrs. Hoving pursued her music career alone and had wide-ranging success, from musical comedy to opera and nightclub engagements as well as her own shows on NBC radio and ABC television.", 
            "Fewer Roles Ms. Dennis's success was extraordinary for any actor or actress, but even then, she seemed to recognize that such oversized fame might be ephemeral.", 
            "\"Valley of the Dolls\" (1967) was a steamy box office success but critically scorned.", 
            "Ms. Dennis's success was extraordinary for any actor or actress, but she seemed to recognize that such oversize fame might be ephemeral.", 
            "\" Mr. Abbott built up the \"blind date\" role in \"Best Foot Forward\" from five lines to a leading role, making her an instant success.", 
            "After her success in \"Best Foot Forward,\" M-G-M flew her to Hollywood and signed her to a seven-year contract.", 
            "They won the first World Women's Pairs Championship in Cannes, France, in 1962, and repeated that success in Las Palmas in the Canary Islands in 1974, a double achievement that has never been matched.", 
            "She also appeared on Broadway, achieving her most notable success in a two-season run of \"Milk and Honey,\" a hit musical that opened in 1961, when she was in her mid-60's.", 
            "Miss Dietrich began her cabaret performances in 1954, and for more than two decades, for fees up to $30,000 a week, she hypnotized audiences in such disparate cities as London, Las Vegas, Paris, New York, Montreal, Johannesburg and Tokyo and Tel Aviv (where she sang in German with some apprehension, but with stunning success).", 
            "A native of Chicago and a 1944 graduate of Cornell University, Ms. Baer scored her first success as an author in 1965 when Macmillan began \"Follow Me!,\" a travel guide for single women looking for a husband abroad.", 
            "Together with her husband, John F. Raynolds 3d, former president of Outward Bound USA, she wrote \"Beyond Success -- How Volunteer Service Can Help You Begin Making a Life Insead of Just a Living.", 
            "The success of their effort was evident at her funeral there yesterday, where Muslims from Pakistan and Morocco prayed shoulder to shoulder with American black converts.", 
            "\"Why not enjoy Hazel's success?", 
            "She was drawn to music and acting early in life, but did not set her sights on an operatic career until she had achieved some modest success as a popular singer.", 
            "Miss Kirsten's Metropolitan Opera debut, as Mimi in \"La Boheme\" on Dec. 1, 1945, was a critical success, and was the start of a 30-year association with the house.", 
            "Part of the success of her teaching lay in her pithy instructions to students.", 
            "Her first success was with the 1948 \"Ballet Ballads,\" a suite of dances she created with Katherine Litz and Paul Godkin to music composed by Jerome Moross, with lyrics by John Latouche.", 
            "As a result of the success of her dance, \"The Eccentricities of Davy Crockett,\" Miss Holm was invited to choreograph \"Kiss Me, Kate\" in 1948 and won a New York Drama Critics Award.", 
            "She found he had revised his theories to stress that the actor should create by imagination rather than by memory and that the key to success was \"truth, truth in the circumstances of the play.", 
            "In the Group Theater, Miss Adler won high praise for performances in such realistic dramas as \"Success Story\" by John Howard Lawson and two seminal Clifford Odets plays, \"Awake and Sing!"
        ], 
        "height": 270, 
        "rate": 18, 
        "start_y": 263, 
        "id": 5
    }, 
    {
        "sentence_index": 0, 
        "sentences": [
            "\" George Jean Nathan, the Broadway critic who courted Miss Gish without success for more than a decade, compared her to Eleonora Duse.", 
            "All of Griffith's Biograph actors were moved around in this way: it was not until after the success of \"The Birth of a Nation\" that any received on-screen credit.", 
            "After its success, the same formula was applied to \"Gold Diggers of 1933\" and \"Footlight Parade,\" which also teamed Miss Keeler with Powell, and again had choreography by Berkeley and songs by Harry Warren and Al Dubin.", 
            "Lights Dimmed on Broadway In tribute to the actress, who was often called the First Lady of the American theater, Broadway marquees were dimmed for one minute last night at 8 P.M. Miss Hayes's greatest stage success was the 1935 drama \"Victoria Regina,\" in which she played the long-lived British monarch from girlhood to widowhood, aging visibly from act to act thanks to the makeup artist's skill, and her own.", 
            "Her first great success was in \"Coquette\" in 1927, and her last was in the 1970 revival of \"Harvey.", 
            "\" Her own view of her success and eminence was modest.", 
            "Later that year she acted in \"Mr. Gilhooley,\" a flop, and \"Petticoat Influence,\" which was only a moderate success, as was \"The Good Fairy\" in 1931.", 
            "Miss Anderson's return to Town Hall on Dec. 30, 1935, was the success that Hurok told her it would be.", 
            "She had an early success in the lead role in \"Shanghai Gesture\" at the Martin Beck Theater on Broadway.", 
            "\" The concept proved a popular success.", 
            "After that success, she became the executive director of the Great Falls Development Corporation and worked to preserve the mills, which were built in the early 1800's and used the water power of the 77-foot-high Great Falls.", 
            "\" It was her biggest success outside the Yiddish theater, and it came when she was 74.", 
            "Danced the Lead In Her Own 'Rodeo' Her first great popular success, however, came in 1942 when she choreographed \"Rodeo\" for the Ballet Russe de Monte Carlo."
        ], 
        "height": 160, 
        "rate": 11, 
        "start_y": 318, 
        "id": 6
    }, 
    {
        "sentence_index": 0, 
        "sentences": [
            "One notable success was the National Institutes of Health in Bethesda, Md.", 
            "\" The success of \"Blues in the Night\" led to roles in several movies, including \"Up In Arms\" (1944) and \"Till the Clouds Roll By\" (1946).", 
            "Then, with the more elaborate \"Dinah Shore Chevy Show\" in 1956, she became one of the few female entertainers to have long-term success as the host of a television variety program.", 
            "The production was an immediate success.", 
            "Her success led her husband to try his hand, as well.", 
            "The Wolffs' first success in the United States was a new edition of the Grimm fairy tales, in 1944.", 
            "Miss Mercouri, whose greatest screen success was her role as a flamboyant prostitute in the 1960 film \"Never on Sunday,\" was 68, her family said, although references disagree on the year of her birth.", 
            "But he wrote that she possessed a \"fiercely independent inner life which she shared with few people and would one day be partly responsible for her enormous success.", 
            "She told a friend that she admired his \"strength and his success.", 
            "\" Her success in that role brought her offers from British film makers.", 
            "She is survived by two daughters: Judith of Kew Garden Hills and Marcia Williams of Lake Success, L.I.", 
            "After performing with the Second City comedy troupe in Chicago, she moved to New York in 1981, where she became an Off Broadway success with her 1985 revue \"Danitra Vance and the Mell-o White Boys.", 
            "Although Ms. Fisher's work tended to be small, she was beginning to enjoy success for her public commissions.", 
            "The success that followed was fueled by her taste, talent and strength of will.", 
            "It was not until the 60's that she began writing poetry in earnest, initially without success.", 
            "\" In the years between, she and Mr. Cronyn, played opposite each other in success after success to become the most illustrious theater couple of their day.", 
            "Ahead of her was more success in nightclubs, cabaret and theater.", 
            "Her belief that there was material for dance in the everyday lives of black people -- and her strong personality and early success -- had a profound influence on several generations of black choreographers and dancers, among them Donald McKayle and Alvin Ailey.", 
            "\" The show became an instant success and made Miss Baker an international star."
        ], 
        "height": 254, 
        "rate": 17, 
        "start_y": 271, 
        "id": 7
    }, 
    {
        "sentence_index": 0, 
        "sentences": [
            "She was 91 and lived in Lake Success, N.Y. Mrs. Raffa was born in Sicily and came to New York City in 1928.", 
            "In addition to Matilda, who lives in Manhattan, she is survived by another daughter, Nancy Mazzola, of Montville, N.J.; three sons, Frank, of Lake Success; Sam, of Syosset, L.I., and Joseph, of San Diego, 15 grandchildren and 18 great-grandchildren.       ", 
            "Since then, other researchers have also reported success in training chimpanzees to communicate without depending on speech, as by pushing specific buttons on a keyboard.", 
            "She wrote articles about home-school partnerships and promoting the academic success of children from diverse ethnic backgrounds.", 
            "Her books in print are \"Managing an Effective Interview Program\" (Teachers College, 1984), \"Parent Involvement and Success for All Children: What We Know Now\" (Institute for Responsive Education, 1990), \"Schools Reaching Out and Success for All Children: Two Case Studies\" (Institute for Responsive Education, 1990), and \"Developing Home-School Partnerships: From Concept to Practice\" (Teachers College, 1993).", 
            " Sylvia Weinberger, who used a sprinkling of matzoh meal, a pinch of salt and a dollop of schmaltzmanship to turn chopped liver into a commercial success, died on July 23 at a hospital in Fort Lauderdale, Fla. She was 89 and had lived in Boca Raton, Fla. Mrs. Weinberger started making chopped liver for a luncheonette she and her husband, Irving, had opened in 1944 on the Grand Concourse at 169th Street in the Bronx.", 
            "In a field where creative-writing teachers are judged by the published authors they train, Ms. Hadley assured herself a measure of instant success.", 
            "Miss Chang, who was forced by the Japanese invasion to abandon her college education in Hong Kong, enjoyed a measure of popular success after returning to Shanghai, but her works were dismissed as mere romances until her 1943 novella, \"The Golden Cangue\" (named for a form of restraint resembling the stocks used in colonial America), established her literary reputation.", 
            ") Since then, her success has come steadily.", 
            "\" That success started the sisters on a long series of novelty hits that included \"Ti-Pi-Tin,\" \"Hold Tight,\" \"The Jumping Jive,\" \"Beer Barrel Polka,\" \"Boogie-Woogie Bugle Boy\" and \"Apple Blossom Time.", 
            "After her initial success, she moved back and forth between theater and films.", 
            "Mrs. Greenberg traced her success to a day in 1957 when her 16-year-old daughter, Mary Jane, came home raving about the performance of four classmates at a Passaic High School assembly.", 
            "The Tiara release of \"I Met Him on a Sunday\" was such an immediate success.", 
            "Within a decade, as major labels came to dominate the distribution network, Scepter's success had faded, and by the time the company folded in 1977 Mrs. Greenberg had lost everything.", 
            "As a member of Col. W. de Basil's Ballets Russes from 1932 to 1937, she was  a favorite of the choreographer Leonide Massine, who created major roles for her in two of his monumentally scaled symphonic ballets of the 30's, \"Les Presages\"  and \"Choreartium,\" both of which have recently been revived with success.", 
            "\" Despite the success of \"Gone With The Wind,\" Ms. McQueen found it increasingly difficult to find work in film and theater.", 
            " Lillian Teit Zabar, who fled the pogroms of her homeland, came to the United  States and became part of an American success story, died yesterday in Manhattan.", 
            "His mother's life was \"the classic American success story,\" Saul Zabar said last night.", 
            " Lillian Teit Zabar, who fled the pogroms of her homeland, came to the United  States and became part of an American success story, died Friday in Manhattan.", 
            "Her last living son, Edward M. Kennedy, eulogized the mother of a President, two Senators and an Ambassador and the grandmother of two United States Representatives and the Lieutenant Governor and a state representative in Maryland, saying, \"She was ambitious not only for our success, but for our souls.", 
            "\"It means a great deal to know Negroes are making a success in every phase of life,\" Mrs. Taylor said in 1967.", 
            "Her most important success was a victory in the National Board-a-Match Teams, now called the Reisinger Teams, in 1944.", 
            "The instant success of the play, Ms. Resnik's first, took even the author by surprise.", 
            "Selena's father had toured nightclubs across Texas in the 1960's with the original version of Los Dinos but did not achieve wide success until he made young Selena, with her belting vocal power, the lead singer.", 
            "Reviewers attributed her enduring success to a dualistic personality -- tough versus vulnerable, ingenuous versus calculating -- and to a talent for mimicry and pretense.", 
            "Her boutique became such a success that he abandoned his academic career."
        ], 
        "height": 302, 
        "rate": 20, 
        "start_y": 247, 
        "id": 8
    }, 
    {
        "sentence_index": 0, 
        "sentences": [
            "Miss Laye made her stage debut at the age of 15 and enjoyed her first big success in \"The Merry Widow\" in 1923.", 
            "She spent the next six years as  a radar engineer with Sperry Gyroscope's Advanced Studies Department in Lake Success, N.Y. She held patents on radar receivers.", 
            "She also appeared in more than 50 movies, most of them Mexican musicals of indifferent quality that owed their commercial  success to her remarkable popularity and her dark, keening voice.", 
            "Several prominent politicians, including Senators Sam Ervin and  Jesse Helms, tried without success to get Presidents to nominate her to the nation's highest court.", 
            "However, despite the enormous success of her screenplay for Alain Resnais's 1960 classic, \"Hiroshima, Mon Amour,\" few of the  19 movies she wrote and directed herself did well, not least because words often entirely replaced action.", 
            "\" Even at the pinnacle of success, earning $500,000 to $1 million a year, Mrs.  Bombeck made cleaning house, grocery shopping and cooking dinner a part of her weekly routine.", 
            "Encouraged by friends, Miss Travers published \"Mary Poppins,\" which was an immediate critical success.", 
            "Ms. O'Donnell produced and directed several films, but her greatest critical  success came with \"Crumb,\" a dark portrait of the underground cartoonist Robert  Crumb and his family.", 
            "Miss Garson became an instant success as a captivating young wife in the sentimental 1939 film \"Goodbye, Mr.", 
            "Her success  was recorded later that year on the ABC television show \"Incredible Saturday,\" and she appeared at benefits for the American Cancer Society and the City of Hope Medical Center.", 
            "In fact, she said, the act \"has been one of the biggest success stories of the conservation movement in America,\" contending that many myths had been spread about the act's supposedly onerous effects.", 
            " Faithful followers of soap operas have learned over the years that after a brief and bitter first marriage a young single mother can find love, marriage and singular professional success with a much older man, but now the question is: Can a career woman who sacrificed her leisure to keep a nation of enthralled  housewives glued to their radios for the better part of two decades survive a heart-wrenching regimen of producing as many as 90 cliff-hanging episodes a week to live a full, rich and long life?", 
            "It was a reflection of the grip the Hummerts had on their audience that their programs generated more than five million letters a year, and it was a measure of their commercial success that by 1939 Hummert programs accounted for more than half the advertising revenues generated by daytime radio.", 
            "\" From 'The Lady Lies' To the Milk of Asses Miss Colbert had her first film success in 1929, as the heroine of the talkie \"The Lady Lies.", 
            "\" Miss Colbert's most noteworthy stage vehicles included \"The Barker\" (1927), a box-office hit in which she played an alluring snake charmer; Eugene O'Neill's \"Dynamo,\" which was produced by the Theater Guild in 1929 and won her considerable prestige, although it was not a popular success, and the fluffy comedy \"The Marriage-Go-Round,\" a smash hit that opened in 1958 co-starring Charles Boyer, with whom she had also appeared in such films as \"Private Worlds\" (1935) and \"Tovarich\" (1937).", 
            "An important ingredient in her early success in the theater was her skill asa speaker.", 
            "Mrs. Mason said that part of her later success was that she left school at age 9; education, she said, only confuses the mind.", 
            "The maps were an instant success, and have sold countless millions of copies since, the favorite of visitors and Londoners alike, including the cab drivers and others whose job it is to make their way around the city.", 
            "But Annabella achieved only minor success in her adopted country.", 
            "Lear's began publication in 1988 and was a success.", 
            "She had her greatest success as June Buckridge in Frank Marcus's ''Killing of Sister George.", 
            "'' She credited her husband, Lionel Trilling -- one of the century's foremost literary critics and teachers and the author of works like ''The Liberal Imagination'' that became central documents of American intellectual life -- with her success and development as a critical writer, even as she struggled to establish herself in her own right in later years."
        ], 
        "height": 192, 
        "rate": 13, 
        "start_y": 302, 
        "id": 9
    }, 
    {
        "sentence_index": 0, 
        "sentences": [
            "The book's success finally gave Ms. Hanff the wherewithal to travel to England, where she visited the boarded-up bookshop and met Mr. Doel's widow, Nora, a journey documented in ''The Duchess of Bloomsbury Street'' (1973).", 
            "'' With its games and lessons, the show was an instant success.", 
            "Neither enjoyed the critical or commercial success of her first novel, however, and from then on Mrs. Petry, by then a mother, turned out books for children and young adults, among them two biographies, ''Tituba of Salem Village,'' and ''Harriet Tubman: Conductor on the Underground Railroad.", 
            "That small success made her decide on writing as a career.", 
            "Instead, Dr. Hibberd will start a new job Monday as a senior executive at Ipro, a health-care consulting firm in Lake Success.", 
            "That the competitive history between the two northern Californians was called a rivalry, dubbed the Battle of the Helens by a sometimes frothy news media between the two world wars, was a tribute more to  Jacobs's tenacity and cheerful pluck than to her shot-making power or on-court success against Moody.", 
            "The success that eluded Mrs. Westwood in politics came to her in business.", 
            "'' Her success, he said, ''depends on the exploitation of the simple and the humble by the cunning and the single-minded.", 
            "''Some parents still blame themselves when they discover their child is retarded,'' she said, and then go from doctor to doctor looking for a ''cure,'' rather than counseling that will help them teach their children to learn to function with some degree of success.", 
            "'' Ms. Dickerson often acknowledged over the years that her success came partly from knowing people.", 
            "She did so with notable success: her recordings as a soprano show her to have a clear timbre and considerable power.", 
            "He acknowledged her success with thanks in his preface."
        ], 
        "height": 114, 
        "rate": 8, 
        "start_y": 341, 
        "id": 10
    }, 
    {
        "sentence_index": 0, 
        "sentences": [
            "For all her success in the United States, Miss Karff, who was forever sailing off to Europe or South America for tournaments, fared less well in top international competition.", 
            "For those moments of success, it's worth the price.", 
            "After she won her Olympic gold medal, her husband, Aurel Naicu, who had limited success as a discus thrower and coach, bought an expensive American car in Mexico City and sent it to Bucharest.", 
            "'' With the rise of the black power movement and the success of independence movements in Africa and the Caribbean, interest in the Schomburg grew.", 
            "The success of the book and of the television series, which ran from 1962 to 1968, helped persuade Mrs. Kampen to continue mining her life for comedy.", 
            "She reported on the fledgling United Nations and its agencies in Lake Success, N.Y., the interim headquarters of the organization.", 
            "''I already had a major success in Europe.", 
            "In the capricious world of show business, she never enjoyed splashy success, but in the backwaters of her profession, where most singers, after all, spend their entire careers, Miss Cisyk, a tiny, slender woman with a smile as big as her heart, made her share of waves.", 
            "She found greater success in her solo career; Cashbox magazine named her Top Female Country Vocalist of 1963.", 
            "The extraordinary success that followed propelled Mr. Dilenschneider to the top of Hill & Knowlton, the world's largest public relations firm, and Ms. Connelly rose to become its first female executive vice president and head of worldwide business development.", 
            " Helen Ward, who sang with the Benny Goodman band in the 1930's, died on April 21 at the Vencor Hospital in Arlington, Va. She was 82 and lived in Falls Church, Va. Ms. Ward's supple voice, her easygoing sense of swing and her alluring stage presence were essential to the Goodman band's early success.", 
            "Its success and her succinct prose led Mr. Chujoy to invite her to Dance News.", 
            "'' Success in summer stock eventually led to Broadway, and opening night was filled with minor disasters.", 
            "'' Mr. Lindsay attributed the phenomenal success to the fact that the play was not just a comedy but also had a tender, familial side: ''People who see 'Life with Father' are emotionally moved as well as amused.", 
            "'' To some latter-day feminists, Miss Polykoff was somewhat perplexing, on the one hand an obvious pioneering role model for professional women, on the other a woman whose success, which included such campaigns as ''Is It True Blondes Have More Fun?", 
            "For all her ambition and outsized success as a woman, Miss Polykoff was cut from a pre-feminist mold, never forgetting, as she often put it, that she was ''a girl first and an advertising woman second.", 
            "Her first success came with ''The Incredible Journey,'' a novel by Sheila Burnford about the travels of two dogs and a cat across the Canadian wilderness.", 
            "In a business world where women have had to pick their way through contradictory advice on how to dress for success, Sister Irene never had a wardrobe worry.", 
            "With her strawberry blond hair, gleaming smile and rich Oklahoma twang -- Mrs. Carnegie was a student of Mr. Carnegie as well as his wife -- she proved as big a success in business as he was in motivational speaking.", 
            "Mrs. Blumkin stood just 4 feet 10 inches in her prime, but her merchandising skills and daring as she made the long journey from an impoverished childhood in Russia to success led figures like Warren E. Buffett to rank her as a business giant.", 
            "Some of her colleagues predictably complained that the course's success was based more on showmanship than scholarship, but Dr. Butler, many of whose students went on to to teach children's literature at other colleges, was no slacker as a scholar.", 
            "As a reporter and editor for The Washington Star for 15 years, Ms. House had won visibility and success covering the District of Columbia Police Department and local courts, one of the few women at the time to work that beat.", 
            "Though Miss Hickson acted in more than 80 movies and had a considerable stage career, it was as Miss Marple, a role she took on in her late 70's, that she achieved her most success and her greatest renown.", 
            "Though Dr. Calderone saw serendipity as a major architect of her success, she did not always lead a charmed life.", 
            "It was not a success and she did not build again.", 
            "The success of the Andrew Lloyd Webber musical ''Evita'' in the 1970's and the appearance of the movie version in 1996 revived interest in Ms. Main's book, and it was republished several times in the United States and Britain.", 
            "That role, The Daily Telegraph said on Saturday, was her greatest success, and ''as an actress, she knew, like Garbo, when to quit.", 
            "Her success with their dream was such that when the center turned 50 in 1993 and called itself ''a glorious home for dance, music, opera and dozens of extraordinary musicals and plays,'' there were many who thought the phrase an understatement of what Miss Dalrymple had accomplished.", 
            "Encouraged by this success, she wrote more stories for a Philadelphia paper, receiving $5 for each one.", 
            "The season was a critical and box-office success.", 
            "As a producer, Miss Dalrymple tended to play down her adroit handling of the press, which is critical in the success of even the most expertly produced play.", 
            "At the time, the play's director, Jacques Hebertot, predicted, ''You will carry this role throughout your life, a slave to the success it will bring you.", 
            "In a career that began in 1935, Ms. Godden published some 70 novels, children's books, memoirs, biographies and collections of poetry and  stories, many set in India, where she spent her childhood and had her first success as a writer.", 
            "Ms. Godden's third novel, ''Black Narcissus'' (1939), first brought her critical attention and commercial success.", 
            "The key to her success in therapy with Indian patients was her understanding of the importance placed on a balance of life's forces, and she often asked family members to join in the therapy, Dr.", 
            "Then she guided the show to its Broadway success."
        ], 
        "height": 316, 
        "rate": 21, 
        "start_y": 240, 
        "id": 11
    }, 
    {
        "sentence_index": 0, 
        "sentences": [
            "With a naturalness and an authority that belied her limited theatrical experience, she was an astonishing success in her first major role.", 
            "Ms. Verrill, who had already recorded the film's soundtrack, suddenly found herself ousted by the actress of the moment, Andrea Leeds, who had become an overnight success that year in ''Stage Door.", 
            "She wrote her first book in 1923, and her early writing met with critical success while causing scandal with its emphasis on subjects like rape, infanticide, lesbianism and abortion.", 
            "The success of her painting helped soften the blow when the movie ''Rhapsody in Blue,'' came out in 1945 and excised her and Arthur from the Gershwin family.", 
            "The theater, which has had a policy of presenting bold new playwrights since its 1956 success with John Osborne's groundbreaking  ''Look Back in Anger,'' stuck by Ms. Kane and staged two of the three other plays she was to write in her short, high-profile career.", 
            "The young wife hoped that Time's growing success would eventually allow her workaholic husband to join her in the kind of social whirl she loved.", 
            "'' Miss Lortel was frustrated by the success of ''Threepenny Opera'' because she wanted to bring more plays into her theater, so she  persuaded the American National Theater and Academy to support a matinee series as a ''laboratory for innovation.", 
            "'' She had her greatest success with ''Superior Women'' in 1984, which became a best seller and traced the lives of five Radcliffe women from 1943 to 1983.", 
            " Sara Holmes Boutelle, an architectural historian who rediscovered Julia Morgan, one of the first female architects to achieve major success, died on Wednesday at the Dominican Hospital in Santa Cruz, Calif. She was 90.", 
            "''I didn't foresee my success,'' she later recalled.", 
            "But Danieli's business success reflected her drive for technical superiority and her untiring sales efforts.", 
            "That's not what we were about, and that's not the secret of our success.", 
            "''You, who as an irreproachable and decent athlete, did everything you could to achieve athletic success, were already stamped by the Nuremberg Laws as a second-class person, and for renouncing athletic success in order to show solidarity with the persecuted, you were punished.", 
            " Anne Woolliams, a British ballet teacher who played a major role in the international success of the Stuttgart Ballet and who became artistic director of the Australian Ballet and the Vienna State Opera Ballet, died in Canterbury, England, on July 8.", 
            "'' During the 1940's and 1950's, their children said, the couple's success rate was so high that their participation in a forthcoming show was enough to guarantee its full funding.", 
            "The performance was such a success that soon she and her sisters were regularly singing with the Carter Family on the Texas station XERA, a powerful radio broadcast set up mainly so that a quack doctor could advertise his unusual remedies for impotence.", 
            "But the success of college women's basketball, coupled with the Olympic championship team at the 1996 Atlanta Games, put women's basketball on the American sports map.", 
            "The television show took them to new heights of success.", 
            "Ms. Dickson Wright agreed, although she credited the success of the show to a backlash against what she called the health police.", 
            "The success of the Little Rock campaign, she later said, ''had a lot to do with removing fear that people have for getting involved.", 
            "'' The Cadet Nurse Corps proved a success, meeting its recruitment quotas in 1943 and 1944 and outstripping them in the final year of the war, when there were 112,000 cadets in the program.", 
            "Explaining the success of the Cadet Nurse Corps, Ms. Leone told an interviewer in 1945: ''We had a saleable package from the beginning."
        ], 
        "height": 238, 
        "rate": 16, 
        "start_y": 279, 
        "id": 12
    }, 
    {
        "sentence_index": 0, 
        "sentences": [
            "Israel's prime minister, Ehud Barak, said she represented the Israeli success story.", 
            "The breakthroughs achieved by Ms. Cashin and designers like Claire McCardell, Vera Maxwell, Anne Klein and Anne Fogarty still influence the way women dress, and paved the way for the success of American designers like Ralph Lauren, Donna Karan and Calvin Klein.", 
            "Sarah had this incredibly sharp brain, which was evidenced by her success at both navigating and portraying what someone in Oliver Cromwell's Parliament once called 'the tortuous, ungodly jungle of English law.", 
            "Although Ms. Matthiasdottir enjoyed both critical and financial success in New York, especially after 1970, official recognition proved elusive.", 
            "She was one of several postwar artists who, despite Abstract Expressionism's unanimous success, persisted in the notion that abstraction and representation were not mutually exclusive states, that one could paint from reality in a way that gave form, color and paint a power all their own.", 
            "They also mingled at Ms. Howard's Spanish-style home on Coldwater Canyon Drive in Beverly Hills; she and her first husband, Charles K. Feldman, who used his success as the first super-agent to become a producer, bought it for $18,000 in 1942.", 
            "Mrs. Reed, who wrote some 250 compositions, ranging from songs to marches to operas, achieved her widest success with the 1953 pop song ''Oh, Happy Day,'' which she co-wrote with Don Howard Koplow.", 
            "'' Yet Anna Kisselgoff said in The New York Times in 1976 that ''the secret of her success is the way she distills emotion into a few movements.", 
            "Although a misinformed press agent billed her as a Russian ballerina, her success led her to stay on and found a modern-dance company, La Paloma Azul, in 1940.", 
            "''When you have success and you're having fun, it just snowballs and gets bigger and bigger,'' Schmirler said of the team's success.", 
            "In the early 1950's she began to achieve critical and popular success onstage in France, where she starred in productions like ''The Rose Tattoo,'' ''A View From the Bridge,'' ''A Taste of Honey'' and ''The Brothers Karamazov.", 
            " Thea Porter, one of the earliest  among British fashion designers who rode hippie chic to high visibility, if not always to enduring commercial success, died on Monday in London.", 
            "The friend said Sister Isolina's success as a peacemaker was the result of her interpersonal skills, her training in sociology at Fordham and the insights provided by her Puerto Rican heritage.", 
            "Ms. Verdon's first Broadway success was explosive.", 
            "She wasn't eager to return to Broadway despite her success in ''Can-Can,'' but finally signed on.", 
            "It would be her first experience with an up-and-coming choreographer named Bob Fosse, fresh from his first Broadway success with ''The Pajama Game.", 
            "When Mr. Kidd made his offer of a part in ''Can-Can,'' she was weary of anonymity, weary of Cole -- a perfectionist given to tantrums -- and ready to leave Hollywood for a second chance at success on Broadway.", 
            "'' In many cases, the shows went on to wide success, like ''Juan Darien,'' which began Off Off Broadway and eventually reopened at Lincoln Center and led to Ms. Taymor's being asked to direct ''The Lion King'' on Broadway."
        ], 
        "height": 192, 
        "rate": 13, 
        "start_y": 302, 
        "id": 13
    }, 
    {
        "sentence_index": 0, 
        "sentences": [
            "'' But her tasteful furnishings reflected her success in saving and investing her sideshow income.", 
            "''It was quietly marvelous, sort of like Mozart,'' said Peter Workman,  the publishing house president, of the book's success.", 
            "The success of the first book led the three to answer readers' pleas for help after birth.", 
            "'' Anne Morrow Lindbergh scored an immense literary success in midlife with her 1955 book ''Gift From the Sea'' ( Pantheon), which was a philosophical meditation on women's lives in this century.", 
            "When half a dozen bit parts in movies got her nowhere, she tried Broadway with somewhat more success.", 
            "In 1982 she scored another film success in ''Poltergeist'' as a psychologist moonlighting as a parapsychologist.", 
            "And her private life was shadowed  by her success and her travels as an actress.", 
            "'' In June 1998, after earlier success in dismantling a drug operation at the Castle Hotel at 106th Street and Central Park West, she was assigned to take on the Black Top gang, named for the color of the caps on their crack vials.", 
            "'' At the height of her success, Ms. Coca, who won an Emmy as the best actress of 1951, was making $10,000 a week.", 
            "Mrs. Graham's courage in supporting her reporters and editors through the long investigation was critical to its success.", 
            "When she returned to La Scala in 1929, under the name Gina Cigna, she had a great success as Donna Elvira in Mozart's ''Don Giovanni'' and a few weeks later as Elisabeth in Wagner's ''Tannh\u00e4user.", 
            "For many years, she was a moderator and host of radio and television programs under the titles ''Focus on the Black Woman'' and ''In the Black: Keys to Success.", 
            "But the success of the exotic electronic instrument seems to have been diminished by small number of players.", 
            "She appeared in ''A Clearing in the Woods,'' ''A Touch of the Poet,'' ''Cheri,'' ''A Far Country'' and ''The Three Sisters,'' among other plays, but nothing came close to her success in ''Bus Stop'' except her performance in the 1958 film ''The Goddess,'' one of her rare forays into Hollywood.", 
            "Performance pressures also began to take their toll, and even after her shining success in ''Bus Stop,'' stories began to circulate about her profound malaise each night at curtain time.", 
            "Against other disabled skiers, her success was overwhelming.", 
            "'' Two years later she scored a London success as Queen Victoria in ''Portrait of a Queen.", 
            "She then went to Houston, where surgeons had reported success in rarely performed surgery for cancerous heart tumors.", 
            "These include ''Children's Experiences Prior to First Grade and Success in Beginning Reading,'' ''Young Children's Thinking: Studies of Some Aspects of Piaget's Theory'' and, with Celia Genishi, ''Ways of Studying Children: An Observation Manual for Early Childhood Teachers.", 
            " Dorothy McGuire, who came to Hollywood from Broadway to repeat her 1941 stage success in the title role in ''Claudia,'' and went on to have a long and distinguished film career playing sensitive, intelligent and steadfast women, died yesterday in Santa Monica, Calif. She was 83.", 
            "She was right; the production was a great success.", 
            "''The Heiress,'' an adaptation of the Henry James novel ''Washington Square,'' brought the Goetzes great success when it opened on Broadway in 1947.", 
            "Soon it was an international success both on the stage and on the screen, and, Mrs. Goetz said, ''it gave James, long in his grave, the best seller he never had.", 
            "She began her acting career in 1944 in repertory theater in the north of England and traveled all over the country until the success of ''Sailor Beware'' established her reputation.", 
            "''Recognition is the key,'' Mrs. Ash said, explaining her success and how she devised her corporate symbols to reward her sales force.", 
            "One, labeled Ladder of Success, was a gold pin with each rung marked with a jewel.", 
            "Although the product line was added to over the years -- there are now more than 200 items for women and men in skin, hair, nail and body care and sun protection -- the Mary Kay formula for success changed little.", 
            "One, labeled the Ladder of Success, was a gold pin with each rung marked with a jewel.", 
            "Although the product line was expanded over the years -- there are now more than 200 items for women and men in skin, hair, nail and body care and sun protection -- the Mary Kay formula for success changed little.", 
            "The couple followed up its success with ''How to Be Awake and Alive'' (Random House, 1975) and ''How to Take Charge of Your Life'' (Harcourt, Brace, 1977)."
        ], 
        "height": 302, 
        "rate": 20, 
        "start_y": 247, 
        "id": 14
    }, 
    {
        "sentence_index": 0, 
        "sentences": [
            "Whether on the verge of success or not, she was called home to Grey Gardens by her mother, who said she was ill and needed her.", 
            "'' Her success also made her more acceptable to an initially chilly Hollywood film community, which had held her suspect for wartime adventures, later described in her searing memoir, ''The Gift Horse'' (McGraw-Hill, 1971).", 
            "Success was measured by the innumerable Castro convertibles in apartments and houses.", 
            "Her biggest success was surely her idea of using Bernadette, starting at the age of 4, wearing a white nightgown and sausage curls, in television commercials for the sofas.", 
            "The film's success led the team to make ''Joe Leahy's Neighbors'' (1989), about the political and cultural struggles of a mixed-race coffee planter, and ''Black Harvest'' (1992), about land and money disputes and their escalation into tribal warfare.", 
            "Her ''Gef\u00e4ngnistagebuch'' proved to be a particularly enduring success.", 
            "It was a success, but her refusal to join the Nazi Party or any of its affiliates led to her ouster from the writers' guild in 1942.", 
            "Her biographers tend to agree that she was a great success as a debutante, flirting wildly and constantly fending off a large coterie of broken-hearted suitors, one of whom reportedly -- and unromantically -- serenaded her by cracking his hunting whip under her bedroom window at night.", 
            "And Barbie's fly-off-the-shelf popularity transformed the sleepy company that sold the doll, Mattel Inc., into a postwar success story.", 
            "She was cast so often as a notorious or strong-minded woman that those characteristics became indistinguishable from her own tempestuous personality in the minds of many fans, especially after the success of early films with titles like ''Woman Without a Soul.", 
            "It had a solemn induction ceremony, based on a Taino Indian ritual, in which ''aspirantes'' held candles and pledged to pursue educational excellence and to dedicate their success to their community.", 
            "The girls' father was an immigrant from Vladivostok, Russia, who made his start in America selling chickens from a wagon and, in the classic New World success story, wound up owning movie theaters in three states.", 
            "'' The column was an immediate success, and quickly went into syndication.", 
            " Dolores Gray, a singer and actress whose success on Broadway and London's West End led to starring roles in several 1950's Hollywood musical extravaganzas, died on Wednesday in her Manhattan apartment.", 
            "Her first major success was playing the lead in ''Annie Get Your Gun'' in London in 1947.", 
            "'' Her London success led to major Broadway roles.", 
            "In 1948, Betty Clooney quit the Pastor band, but Rosemary stayed with him another year before she left as well, hopeful of success because she had signed a contract with Columbia Records.", 
            "The success emboldened Mr. Miller to assign her to other novelty songs, most notably ''Botcha Me'' and ''Mambo Italiano'' that also became hits.", 
            "At the same time, you can't quarrel with success.", 
            "Rosemary stayed another year before she left, hopeful of success because she had signed a contract with Columbia Records.", 
            "The success emboldened Mr. Miller to assign her to other novelty songs, most notably ''Botcha Me'' and ''Mambo Italiano,'' which also became hits.", 
            "''She was vitally interested in the company and its success and its maintaining its journalistic independence and standard of accuracy in its news reporting,'' he said.", 
            "Even as Ms. Slobodkina found success in writing and illustrating books, she continued her paintings, textiles and sculptures.", 
            "Her stubbornness was vindicated when her Museo Dolores Olmedo Pati\u00f1o, on the southern outskirts of Mexico City, was judged an artistic success.", 
            "The improvised ''Oh What A Lovely War,'' which brought Theater Workshop its greatest success, was a satire of World War I done in 1963 as a music hall revue with the actors in black-and-white commedia dell'arte costumes.", 
            "'' She also gave William Saroyan's ''Sam, the Highest Jumper of Them All'' its world premiere, enjoyed success with Wolf Mankowitz's ''Make Me an Offer'' and the ex-convict Frank Norman's ''Fings Ain't What They Used to Be,'' and discovered talent that ranged from John Bury, later the National Theater's head of design, to Richard Harris, who played Macbeth for her.", 
            "She was already an academic and social success at Oxford University when John Betjeman, one of the many literary figures she befriended, called her ''the aesthetes' moll.", 
            "She received good reviews for her history ''Jameson's Raid'' in 1960 and then achieved widespread success with the biography ''Victoria R.", 
            "Her first big stage success came in 1942 in Terence Rattigan's ''Flare Path,'' a wartime drama about a bomber base that Winston Churchill called his favorite play.", 
            "But unlike other British actresses of the time, like Vivien Leigh and Deborah Kerr, she did not repeat her British success with American audiences.", 
            "Her athletic success was remarkable considering her health.", 
            "She liked what it brought, especially a Mercedes-Benz and a Malibu home after her 1984 Olympic success.", 
            "Ms. Carroll more than made up for the brevity of that run with two enormous success during the 1970's.", 
            "That show, ''Your Arms Too Short to Box With God,'' with music and lyrics by Alex Bradford and Micki Grant, turned out to be a big success, spawning several national tours and two return trips to Broadway, including a 1982 version starred Patti LaBelle and Al Green."
        ], 
        "height": 378, 
        "rate": 25, 
        "start_y": 209, 
        "id": 15
    }, 
    {
        "sentence_index": 0, 
        "sentences": [
            "She was also the manager of the pianist Alfred Brendel, starting early in his career, and was instrumental in his success in the United States.", 
            "Her biggest success after ''Ain't Misbehavin' '' was the sitcom ''Gimme a Break!,'' in which she played Miss Nellie Ruth ''Nell'' Harper, the housekeeper and surrogate mother for a widowed California police chief and his three children.", 
            "It was not a success, nor was her solo writing effort two years later, a comedy called ''Jenny Kissed Me,'' about a priest who finds his household disrupted by the arrival of his housekeeper's niece.", 
            "Mrs. Kerr scored her first big success outside the theater with the publication in 1957 of ''Please Don't Eat the Daisies,'' a witty and wide-ranging collection of pieces about everything from the pet dogs in her life to the oddities of the Kerrs' house in Larchmont, which boasted a two-story fireplace and a carillon that played the duet from ''Carmen.", 
            "For all her experience and success in the theater, Mrs. Kerr never stopped worrying about how her work would be received.", 
            "'' She once said, ''I think if you can write a play or produce a play,'' the first step toward success has been made, if ''people don't want to kill themselves in the lobby.", 
            "She also had a major London success with Jerome Kern's ''Music in the Air.", 
            "In 1956 she changed the company's name to Eve Stillman, and later it became Eve Stillman Inc. Its products included hand-embroidered nightgowns, and it had particular success with horsehair petticoats for the full-skirted fashions of the 1950's.", 
            " Peggy Conklin, a stage actress who found early success in ''The Petrified Forest'' in 1936 and followed it with a wide variety of dramatic and comic roles on Broadway, died last Tuesday at her home in Naples, Fla. She was 96.", 
            "It was an unexpected success and did much to give that art a wider public and institutional presence.", 
            "Although Balanchine was considered the genius behind much of Ms. Zorina's success onstage and screen in the 1930's and 1940's (they were divorced in 1946), she was better known to the general public than he was in 1938, when they went to Hollywood to work for Sam Goldwyn.", 
            "'' After moving to London to study ballet, she had her first success in the West End in 1933: Anton Dolin, the British ballet star, cast her opposite himself in ''Ballerina,'' a play with ballet interludes.", 
            "'' She ascribed part of her success to her husband and sometime law partner, Hicks G. Griffiths, who was once state Democratic chairman of Michigan.", 
            "MacMillan, the publisher, promoted the book with unusual vigor, hoping to emulate its 1936 success with ''Gone With the Wind.", 
            "'' She wrote seven more novels, but none came close to the success of her first.", 
            "'' Dr. Densen-Gerber's success at getting government help became her downfall when the state investigated her use of public funds in the early 1980's and found irregularities.", 
            "She often limited her film and theater work to be with her family, but remarked to an interviewer that it was ''impossible to make a success'' of both home and career all the time.", 
            "The book, ''Postmortem,'' had been rejected by several publishing houses, but it was a success with the public when it came out in 1990.", 
            "I think I'm a success, but I had every advantage; I should have been.", 
            "Trousers as a Trademark Despite her early success, reviewers in those days sometimes found her strident and mannered.", 
            "A Loving Partnership The success of ''Woman of the Year'' (1942) and the stars' off-screen relationship led to other Tracy and Hepburn films that followed a similar pattern.", 
            "Ms. Welch's decision to remain in Europe and make London her home may have resulted from a combination of her success there, her mother's Scottish and Irish ancestry and a visceral sense of belonging.", 
            "In an interview in Success magazine in 1998, she said her father lost a son in the war.", 
            "The club was an immediate success, but its name, the Body Shop, caused confusion: People thought it was an auto-repair business.", 
            "She understudied Jayne Mansfield in ''Will Success Spoil Rock Hunter?", 
            "Gibson owed much of her success to that very network of black tennis enthusiasts and to a geographic coincidence.", 
            "''Her road to success was a challenging one, but I never saw her back down.", 
            "The success of the Americans helped further the reputation of American design.", 
            "Her book, ''The Past Is Myself,'' published in 1968, was a runaway success and a Book of the Month Club selection as ''Ride Out the Dark'' (Norton, 1971).", 
            "Her success in ''Annie'' came after a life devoted to performing, a career that included television, film and roles in Broadway shows both acclaimed and better off forgotten.", 
            "'' Despite her success, however, she did not think her talents were particularly suited to television.", 
            "Ms. Loudon's success in ''Annie'' led to several more Broadway roles, including ''West Side Waltz'' (1981), opposite Katharine Hepburn, and ''Noises Off'' (1983), as a diva in a sinking production.", 
            "She had not worked as an actress in two years, but her audition was a great success.", 
            "She occasionally wrote for the theater and the movies, though without much success.", 
            "The Bride's Shop, as she called it, was an immediate success, with sales of more than $10,000 in its first week.", 
            "Mrs. Kidder's success put her increasingly in contact with the wealthy."
        ], 
        "height": 456, 
        "rate": 30, 
        "start_y": 170, 
        "id": 16
    }, 
    {
        "sentence_index": 0, 
        "sentences": [
            "'' ''Scarlett,'' which was universally panned by critics, was a considerable commercial success.", 
            "Troy's other songs for Atlantic during this period -- including ''What'cha Gonna Do About It?,'' also recorded by the Hollies -- had more success in Britain than in America, and in the late 60's she moved to London.", 
            "Often, she found that programs had no built-in procedure to evaluate their success.", 
            "She was also a producer of several Tony-nominated plays and musicals, including David Hare's ''Skylight'' in 1996, ''Sweet Smell of Success'' in 2002 and ''The Play What I Wrote'' last year.", 
            "In her 1985 autobiography, ''Est\u00e9e, A Success Story,'' Mrs. Lauder recalled her mother as ''a Hungarian beauty whose mother was a French Catholic and whose father was a Hungarian Jew.", 
            "Mr. Lauter had tried his hand without much success in both the silk and button businesses.", 
            "Peter Kennedy attributed much of the team's success to his father having taught them perseverance.", 
            "Building on the success of ''Gymsuit,'' Ms. Danziger also became a popular speaker.", 
            "Part of her success, too, came from the way she balanced Western and Japanese acting styles.", 
            "Despite their success, the photographers closed their studio the same year, shortly after Hitler came to power.", 
            "Despite her success in Germany, she chose to return to Turkey that year and assist in establishing the first opera house in Ankara.", 
            "'' The key to her success, Ms. Rutherford said, was that she was so flexible: ''She could play the girl next door or somebody's other woman.", 
            "The huge success of ''King Kong,'' a beauty-and-the-beast film that opened in New York at both Radio City Music Hall and the Roxy in 1933, led to roles for Miss Wray in other 1930's films in which her life or her virtue, or both, were imperiled.", 
            "She stayed with WGBH even after her series became a national success because it gave her the freedom to cook tripe, kidneys and other offal that she said would not fly on commercial television.", 
            "When she wrote recipes, they were long and detailed because, she said, she felt obligated to ensure their success.", 
            "Ms. Sagan had an enormous international success with ''Bonjour Tristesse,'' about an amoral teenager who sets out to keep her philandering widowed father from marrying again.", 
            " Jessie V. Stone, a philanthropist who was the widow of W. Clement Stone, the insurance magnate known for his optimistic books and speeches on success, died on Sept. 3 at her home in Winnetka, Ill. She was 100.", 
            "Two earlier galleries -- Alfred Stieglitz's 291 early in the 20th century and Julien Levy's in the 1930's -- had tried to sell photographs but without success.", 
            "Instant success propelled her into appearances in Parma as Puccini's Mimi in ''La Boh\u00e8me,'' her first Desdemona and other roles.", 
            "She was also associate producer of the 1955 comedy ''Will Success Spoil Rock Hunter?"
        ], 
        "height": 254, 
        "rate": 17, 
        "start_y": 271, 
        "id": 17
    }, 
    {
        "sentence_index": 0, 
        "sentences": [
            "Ms. Vel\u00e1zquez's other songs, none of which rivaled the success of ''B\u00e9same Mucho,'' include ''Amar y Vivir'' (''To Love and to Live'') and ''Verdad Amarga'' (''Bitter Truth'').       ", 
            "A tremendous commercial success, ''A Summer Place'' was among the earliest studio films to commodify youthful rebelliousness, though Ms. Dee was hardly an icon of adolescent revolt with her shiny helmet of flipped hair and color-coordinated outfits.", 
            "''Imitation of Life'' was Universal's biggest success of the 1950's, and prompted the studio to reunite Ms. Dee and Turner in the garish crime thriller ''Portrait in Black.", 
            "They had better success a decade later, when they returned with ''The Megilla of Itzik Manger.", 
            "'' Witty and intelligent, she was also notoriously combative and blamed herself for sabotaging her early Hollywood success by battling with studio executives over roles.", 
            "She was not a great success, but the experience led her and Ms. Sosenko to take off for Paris to learn the art of cabaret.", 
            "She was not a great success, but the experience led her and Sosenko to take off for Paris to learn the art of cabaret.", 
            "In London, she was in Joseph Kramm's ''Shrike'' (1953), with Sam Wanamaker; Clifford Odets's ''Winter Journey'' (1952), with Michael Redgrave; Aristophanes' ''Lysistrata'' (1957); Sartre's ''Huis Clos'' (''No Exit,'' 1962); Max Beerbohm's ''Social Success'' (1962); and as Martha, the alcoholic campus wife, in Albee's ''Who's Afraid of Virginia Woolf?", 
            "''It was a basic story -- three or four or five girls start off together, one finds love, one goes crazy and/or dies, and one of them becomes a huge success -- but Rona's take was very up-to-date,'' Mr. Gottlieb said last night in a telephone interview.", 
            "Unlike her rather passive fictional characters, however, the tough-talking Ms. Jaffe was professionally ambitious and openly spoke of her desire to be a success."
        ], 
        "height": 146, 
        "rate": 10, 
        "start_y": 325, 
        "id": 18
    }, 
    {
        "sentence_index": 0, 
        "sentences": [
            "Her heroines -- intelligent and successful but also riddled with self-doubt -- sought enduring love a little ambivalently, but they didn't always find it, and their hard-earned sense of self-worth was often shadowed by the frustrating knowledge that American women's lives continued to be measured by their success at capturing the right man.", 
            "Her first major success came quickly, with ''Uncommon Women'' in 1977, produced by the Phoenix Theater.", 
            "Caf\u00e9 Nicholson became an instant success among fashionistas, bohemians and artists.", 
            "Their praise immediately elevated Ms. Bedford's literary reputation and made the book a commercial success.", 
            "But she was dating a young physicist who felt threatened by her success.", 
            "Ms. Caldwell's longest period of success came in the 1970's, when the company was thriving and her visibility as a conductor was growing.", 
            "She might not have fulfilled her promise, but for a good dozen years Ms. Moffo enjoyed enormous success and won a devoted following at a time when her competition for roles like Verdi's Violetta, Puccini's Mimi and Donizetti's Lucia included Maria Callas, Renata Tebaldi and Joan Sutherland.", 
            "Other actresses were auditioned, without success.", 
            "She told a newspaper: ''He can't sell his lousy paintings, and I have had a lot of success.", 
            "But she achieved her greatest critical success when she read Ms.", 
            "With the success of Kartell, Ms. Castelli Ferrieri and her husband helped fuel the explosion of Italian modern design in the 60's, 70's and 80's, much as her father had galvanized the cultural scene in his day.", 
            "She attributed her lobbying success to what she called her BAT theory: ''I don't beg,'' she said.", 
            "Ms. Church's success was a historic achievement in an industry that had been especially resistant to using any but white models to represent beauty on magazine covers, advertisements and runways.", 
            "The London performances were an enormous success, and she was invited to join the newly founded Covent Garden company.", 
            "Her success brought unprecedented attention to the race.", 
            "'' Her defeat in 1994, coming in a year of sweeping Republican success at the polls nationwide, did not dim her celebrity on the national stage.", 
            "Ms. Russell's was a career that could only have been a success at a time when classical music culture was near the center of popular awareness and public education.", 
            "'' One did, but the marriage was not a success.", 
            "Her first show was in 1959, which was an immediate success.", 
            "After middling success in Hollywood, Eve Harrington is back in New York, determined to revive her career.", 
            "Their next film, ''The Chronicle of Anna-Magdalena Bach,'' was their first international success.", 
            "''Follies'' was only the start of her success with Prince-directed shows: she went on to win Tony Awards for her designs in ''A Little Night Music'' (1973), ''Pacific Overtures'' (1976), ''Grind'' (1985), ''Kiss of the Spider Woman'' (1993) and the 1994 revival of ''Show Boat.", 
            "Ms. O'Day always maintained that her notoriety helped fuel her success, and the music doesn't contradict her.", 
            "The act's success earned them a movie offer, and the Revuers traveled west in hopes of finding instant fame in ''Greenwich Village,'' a 1944 movie starring Carmen Miranda and Don Ameche, in which the newcomers turned out to be virtually invisible.", 
            "Ms. Comden and Mr. Green were definitely on their way up, not to the Bronx but to big-time success.", 
            "After the success of ''On the Town,'' Ms. Comden and Mr. Green tried their hands at writing the book for another Broadway musical.", 
            "They contributed heavily to the success of ''The Band Wagon'' (1953), the Vincente Minnelli musical for which they wrote the witty screenplay."
        ], 
        "height": 270, 
        "rate": 18, 
        "start_y": 263, 
        "id": 19
    }
]